{"player_id":128,"incorrect":[{"music_id":8183,"instances":2,"total":2},{"music_id":9125,"instances":1,"total":1},{"music_id":10468,"instances":1,"total":1},{"music_id":3691,"instances":1,"total":1},{"music_id":4519,"instances":1,"total":1},{"music_id":8553,"instances":1,"total":1},{"music_id":47,"instances":1,"total":1},{"music_id":6707,"instances":1,"total":1},{"music_id":5803,"instances":1,"total":1},{"music_id":11590,"instances":1,"total":1},{"music_id":8491,"instances":1,"total":1},{"music_id":7637,"instances":1,"total":1},{"music_id":76,"instances":1,"total":1},{"music_id":8930,"instances":1,"total":1},{"music_id":1070,"instances":1,"total":1},{"music_id":1346,"instances":1,"total":1},{"music_id":9060,"instances":1,"total":1},{"music_id":9450,"instances":1,"total":1},{"music_id":10346,"instances":1,"total":1},{"music_id":11368,"instances":1,"total":1},{"music_id":11816,"instances":1,"total":1},{"music_id":11123,"instances":1,"total":1},{"music_id":9453,"instances":1,"total":1},{"music_id":11635,"instances":1,"total":1},{"music_id":9384,"instances":1,"total":1},{"music_id":8495,"instances":1,"total":1},{"music_id":8601,"instances":1,"total":1},{"music_id":12031,"instances":1,"total":1},{"music_id":9576,"instances":1,"total":1},{"music_id":6838,"instances":1,"total":1},{"music_id":9883,"instances":1,"total":1},{"music_id":9844,"instances":1,"total":1},{"music_id":1363,"instances":1,"total":1},{"music_id":3688,"instances":1,"total":1},{"music_id":8511,"instances":1,"total":1}],"never_correct":[{"music_id":8183,"instances":2,"total":2},{"music_id":9125,"instances":1,"total":1},{"music_id":10468,"instances":1,"total":1},{"music_id":3691,"instances":1,"total":1},{"music_id":4519,"instances":1,"total":1},{"music_id":8553,"instances":1,"total":1},{"music_id":47,"instances":1,"total":1},{"music_id":6707,"instances":1,"total":1},{"music_id":5803,"instances":1,"total":1},{"music_id":11590,"instances":1,"total":1},{"music_id":8491,"instances":1,"total":1},{"music_id":7637,"instances":1,"total":1},{"music_id":76,"instances":1,"total":1},{"music_id":8930,"instances":1,"total":1},{"music_id":1070,"instances":1,"total":1},{"music_id":1346,"instances":1,"total":1},{"music_id":9060,"instances":1,"total":1},{"music_id":9450,"instances":1,"total":1},{"music_id":10346,"instances":1,"total":1},{"music_id":11368,"instances":1,"total":1},{"music_id":11816,"instances":1,"total":1},{"music_id":11123,"instances":1,"total":1},{"music_id":9453,"instances":1,"total":1},{"music_id":11635,"instances":1,"total":1},{"music_id":9384,"instances":1,"total":1},{"music_id":8495,"instances":1,"total":1},{"music_id":8601,"instances":1,"total":1},{"music_id":12031,"instances":1,"total":1},{"music_id":9576,"instances":1,"total":1},{"music_id":6838,"instances":1,"total":1},{"music_id":9883,"instances":1,"total":1},{"music_id":9844,"instances":1,"total":1},{"music_id":1363,"instances":1,"total":1},{"music_id":3688,"instances":1,"total":1},{"music_id":8511,"instances":1,"total":1}]}