{"player_id":1375,"incorrect":[{"music_id":8875,"instances":4,"total":4},{"music_id":9716,"instances":4,"total":4},{"music_id":3130,"instances":3,"total":3},{"music_id":11808,"instances":3,"total":3},{"music_id":6201,"instances":3,"total":3},{"music_id":8667,"instances":3,"total":3},{"music_id":9459,"instances":3,"total":3},{"music_id":9221,"instances":3,"total":3},{"music_id":6042,"instances":3,"total":3},{"music_id":11725,"instances":3,"total":4},{"music_id":11560,"instances":3,"total":3},{"music_id":10361,"instances":3,"total":3},{"music_id":10900,"instances":3,"total":3},{"music_id":11799,"instances":3,"total":3},{"music_id":10722,"instances":3,"total":3},{"music_id":5998,"instances":2,"total":2},{"music_id":1435,"instances":2,"total":2},{"music_id":797,"instances":2,"total":3},{"music_id":8542,"instances":2,"total":3},{"music_id":8822,"instances":2,"total":3},{"music_id":7685,"instances":2,"total":3},{"music_id":373,"instances":2,"total":2},{"music_id":4649,"instances":2,"total":2},{"music_id":6054,"instances":2,"total":2},{"music_id":6834,"instances":2,"total":2},{"music_id":105,"instances":2,"total":2},{"music_id":42065,"instances":2,"total":2},{"music_id":74,"instances":2,"total":2},{"music_id":10291,"instances":2,"total":2},{"music_id":4115,"instances":2,"total":2},{"music_id":7853,"instances":2,"total":2},{"music_id":9125,"instances":2,"total":3},{"music_id":7704,"instances":2,"total":2},{"music_id":8978,"instances":2,"total":2},{"music_id":4121,"instances":2,"total":3},{"music_id":3688,"instances":2,"total":3},{"music_id":1364,"instances":2,"total":3},{"music_id":10242,"instances":2,"total":2},{"music_id":4242,"instances":2,"total":2},{"music_id":6377,"instances":2,"total":2},{"music_id":2401,"instances":2,"total":2},{"music_id":43166,"instances":2,"total":2},{"music_id":6059,"instances":2,"total":2},{"music_id":6982,"instances":2,"total":4},{"music_id":6421,"instances":2,"total":2},{"music_id":11224,"instances":2,"total":2},{"music_id":11649,"instances":2,"total":2},{"music_id":6375,"instances":2,"total":2},{"music_id":6206,"instances":2,"total":2},{"music_id":613,"instances":2,"total":2},{"music_id":3690,"instances":2,"total":2},{"music_id":10907,"instances":2,"total":2},{"music_id":1069,"instances":2,"total":2},{"music_id":8426,"instances":2,"total":2},{"music_id":91,"instances":2,"total":2},{"music_id":8144,"instances":2,"total":2},{"music_id":4519,"instances":2,"total":2},{"music_id":9879,"instances":2,"total":2},{"music_id":8495,"instances":2,"total":2},{"music_id":5127,"instances":2,"total":2},{"music_id":7955,"instances":2,"total":2},{"music_id":3692,"instances":2,"total":2},{"music_id":57,"instances":2,"total":2},{"music_id":793,"instances":2,"total":2},{"music_id":11177,"instances":2,"total":2},{"music_id":5366,"instances":2,"total":2},{"music_id":1859,"instances":2,"total":2},{"music_id":8781,"instances":2,"total":2},{"music_id":3565,"instances":2,"total":2},{"music_id":10703,"instances":2,"total":2},{"music_id":3964,"instances":2,"total":4},{"music_id":1072,"instances":2,"total":2},{"music_id":6207,"instances":2,"total":2},{"music_id":10194,"instances":2,"total":3},{"music_id":1405,"instances":2,"total":2},{"music_id":4787,"instances":2,"total":2},{"music_id":42492,"instances":2,"total":2},{"music_id":6923,"instances":2,"total":2},{"music_id":6032,"instances":2,"total":2},{"music_id":10764,"instances":2,"total":2},{"music_id":9905,"instances":2,"total":3},{"music_id":11223,"instances":2,"total":2},{"music_id":7856,"instances":2,"total":2},{"music_id":7689,"instances":2,"total":3},{"music_id":11525,"instances":2,"total":2},{"music_id":230,"instances":1,"total":1},{"music_id":10730,"instances":1,"total":1},{"music_id":41496,"instances":1,"total":1},{"music_id":39,"instances":1,"total":1},{"music_id":8218,"instances":1,"total":1},{"music_id":1234,"instances":1,"total":1},{"music_id":8114,"instances":1,"total":1},{"music_id":4710,"instances":1,"total":1},{"music_id":7781,"instances":1,"total":1},{"music_id":10563,"instances":1,"total":1},{"music_id":3385,"instances":1,"total":1},{"music_id":99,"instances":1,"total":1},{"music_id":11148,"instances":1,"total":1},{"music_id":9333,"instances":1,"total":1},{"music_id":1955,"instances":1,"total":1}],"never_correct":[{"music_id":8875,"instances":4,"total":4},{"music_id":9716,"instances":4,"total":4},{"music_id":3130,"instances":3,"total":3},{"music_id":11808,"instances":3,"total":3},{"music_id":6201,"instances":3,"total":3},{"music_id":8667,"instances":3,"total":3},{"music_id":9459,"instances":3,"total":3},{"music_id":9221,"instances":3,"total":3},{"music_id":6042,"instances":3,"total":3},{"music_id":11560,"instances":3,"total":3},{"music_id":10361,"instances":3,"total":3},{"music_id":10900,"instances":3,"total":3},{"music_id":11799,"instances":3,"total":3},{"music_id":10722,"instances":3,"total":3},{"music_id":5998,"instances":2,"total":2},{"music_id":1435,"instances":2,"total":2},{"music_id":373,"instances":2,"total":2},{"music_id":4649,"instances":2,"total":2},{"music_id":6054,"instances":2,"total":2},{"music_id":6834,"instances":2,"total":2},{"music_id":105,"instances":2,"total":2},{"music_id":42065,"instances":2,"total":2},{"music_id":74,"instances":2,"total":2},{"music_id":10291,"instances":2,"total":2},{"music_id":4115,"instances":2,"total":2},{"music_id":7853,"instances":2,"total":2},{"music_id":7704,"instances":2,"total":2},{"music_id":8978,"instances":2,"total":2},{"music_id":10242,"instances":2,"total":2},{"music_id":4242,"instances":2,"total":2},{"music_id":6377,"instances":2,"total":2},{"music_id":2401,"instances":2,"total":2},{"music_id":43166,"instances":2,"total":2},{"music_id":6059,"instances":2,"total":2},{"music_id":6421,"instances":2,"total":2},{"music_id":11224,"instances":2,"total":2},{"music_id":11649,"instances":2,"total":2},{"music_id":6375,"instances":2,"total":2},{"music_id":6206,"instances":2,"total":2},{"music_id":613,"instances":2,"total":2},{"music_id":3690,"instances":2,"total":2},{"music_id":10907,"instances":2,"total":2},{"music_id":1069,"instances":2,"total":2},{"music_id":8426,"instances":2,"total":2},{"music_id":91,"instances":2,"total":2},{"music_id":8144,"instances":2,"total":2},{"music_id":4519,"instances":2,"total":2},{"music_id":9879,"instances":2,"total":2},{"music_id":8495,"instances":2,"total":2},{"music_id":5127,"instances":2,"total":2},{"music_id":7955,"instances":2,"total":2},{"music_id":3692,"instances":2,"total":2},{"music_id":57,"instances":2,"total":2},{"music_id":793,"instances":2,"total":2},{"music_id":11177,"instances":2,"total":2},{"music_id":5366,"instances":2,"total":2},{"music_id":1859,"instances":2,"total":2},{"music_id":8781,"instances":2,"total":2},{"music_id":3565,"instances":2,"total":2},{"music_id":10703,"instances":2,"total":2},{"music_id":1072,"instances":2,"total":2},{"music_id":6207,"instances":2,"total":2},{"music_id":1405,"instances":2,"total":2},{"music_id":4787,"instances":2,"total":2},{"music_id":42492,"instances":2,"total":2},{"music_id":6923,"instances":2,"total":2},{"music_id":6032,"instances":2,"total":2},{"music_id":10764,"instances":2,"total":2},{"music_id":11223,"instances":2,"total":2},{"music_id":7856,"instances":2,"total":2},{"music_id":11525,"instances":2,"total":2},{"music_id":230,"instances":1,"total":1},{"music_id":10730,"instances":1,"total":1},{"music_id":41496,"instances":1,"total":1},{"music_id":39,"instances":1,"total":1},{"music_id":8218,"instances":1,"total":1},{"music_id":1234,"instances":1,"total":1},{"music_id":8114,"instances":1,"total":1},{"music_id":4710,"instances":1,"total":1},{"music_id":7781,"instances":1,"total":1},{"music_id":10563,"instances":1,"total":1},{"music_id":3385,"instances":1,"total":1},{"music_id":99,"instances":1,"total":1},{"music_id":11148,"instances":1,"total":1},{"music_id":9333,"instances":1,"total":1},{"music_id":1955,"instances":1,"total":1},{"music_id":11846,"instances":1,"total":1},{"music_id":9266,"instances":1,"total":1},{"music_id":7355,"instances":1,"total":1},{"music_id":42933,"instances":1,"total":1},{"music_id":42876,"instances":1,"total":1},{"music_id":41583,"instances":1,"total":1},{"music_id":11482,"instances":1,"total":1},{"music_id":2400,"instances":1,"total":1},{"music_id":6161,"instances":1,"total":1},{"music_id":10243,"instances":1,"total":1},{"music_id":43077,"instances":1,"total":1},{"music_id":42546,"instances":1,"total":1},{"music_id":43254,"instances":1,"total":1},{"music_id":866,"instances":1,"total":1}]}