{"player_id":1596,"incorrect":[{"music_id":8949,"instances":12},{"music_id":6245,"instances":12},{"music_id":5437,"instances":12},{"music_id":50618,"instances":12},{"music_id":11292,"instances":12},{"music_id":163,"instances":12},{"music_id":3553,"instances":11},{"music_id":10200,"instances":11},{"music_id":10319,"instances":11},{"music_id":3555,"instances":10},{"music_id":11134,"instances":10},{"music_id":164,"instances":10},{"music_id":9872,"instances":10},{"music_id":10197,"instances":10},{"music_id":7278,"instances":10},{"music_id":2332,"instances":10},{"music_id":7935,"instances":9},{"music_id":20,"instances":9},{"music_id":9280,"instances":9},{"music_id":3962,"instances":9},{"music_id":8687,"instances":9},{"music_id":10320,"instances":9},{"music_id":7022,"instances":9},{"music_id":11283,"instances":9},{"music_id":11126,"instances":9},{"music_id":10664,"instances":9},{"music_id":9967,"instances":8},{"music_id":8373,"instances":8},{"music_id":5055,"instances":8},{"music_id":7992,"instances":8},{"music_id":243,"instances":8},{"music_id":9511,"instances":8},{"music_id":10859,"instances":8},{"music_id":5054,"instances":8},{"music_id":10343,"instances":8},{"music_id":10158,"instances":8},{"music_id":42566,"instances":8},{"music_id":7933,"instances":8},{"music_id":9284,"instances":8},{"music_id":5800,"instances":8},{"music_id":7998,"instances":7},{"music_id":6621,"instances":7},{"music_id":10195,"instances":7},{"music_id":9797,"instances":7},{"music_id":10198,"instances":7},{"music_id":1451,"instances":7},{"music_id":12018,"instances":7},{"music_id":7634,"instances":7},{"music_id":8688,"instances":7},{"music_id":6389,"instances":7},{"music_id":10641,"instances":7},{"music_id":11127,"instances":7},{"music_id":7277,"instances":7},{"music_id":10708,"instances":7},{"music_id":11207,"instances":7},{"music_id":210,"instances":7},{"music_id":10497,"instances":7},{"music_id":6392,"instances":7},{"music_id":12,"instances":7},{"music_id":7985,"instances":7},{"music_id":11547,"instances":6},{"music_id":10443,"instances":6},{"music_id":7640,"instances":6},{"music_id":7639,"instances":6},{"music_id":8941,"instances":6},{"music_id":9278,"instances":6},{"music_id":9876,"instances":6},{"music_id":6619,"instances":6},{"music_id":10199,"instances":6},{"music_id":10642,"instances":6},{"music_id":9027,"instances":6},{"music_id":3689,"instances":6},{"music_id":449,"instances":6},{"music_id":7023,"instances":6},{"music_id":3692,"instances":6},{"music_id":10492,"instances":6},{"music_id":11210,"instances":6},{"music_id":11211,"instances":6},{"music_id":7633,"instances":6},{"music_id":9879,"instances":6},{"music_id":448,"instances":6},{"music_id":3686,"instances":6},{"music_id":7986,"instances":6},{"music_id":10640,"instances":6},{"music_id":6390,"instances":6},{"music_id":10494,"instances":6},{"music_id":5801,"instances":6},{"music_id":2138,"instances":6},{"music_id":8667,"instances":6},{"music_id":42565,"instances":6},{"music_id":16,"instances":6},{"music_id":10,"instances":6},{"music_id":7997,"instances":6},{"music_id":10860,"instances":6},{"music_id":1363,"instances":6},{"music_id":4617,"instances":6},{"music_id":792,"instances":6},{"music_id":9661,"instances":5},{"music_id":3964,"instances":5},{"music_id":8375,"instances":5}],"never_correct":[{"music_id":5437,"instances":12},{"music_id":50618,"instances":12},{"music_id":3553,"instances":11},{"music_id":10319,"instances":11},{"music_id":3555,"instances":10},{"music_id":164,"instances":10},{"music_id":9872,"instances":10},{"music_id":10197,"instances":10},{"music_id":7278,"instances":10},{"music_id":2332,"instances":10},{"music_id":7935,"instances":9},{"music_id":20,"instances":9},{"music_id":10320,"instances":9},{"music_id":7022,"instances":9},{"music_id":11126,"instances":9},{"music_id":10664,"instances":9},{"music_id":9967,"instances":8},{"music_id":8373,"instances":8},{"music_id":5055,"instances":8},{"music_id":243,"instances":8},{"music_id":9511,"instances":8},{"music_id":5054,"instances":8},{"music_id":10343,"instances":8},{"music_id":5800,"instances":8},{"music_id":6621,"instances":7},{"music_id":10195,"instances":7},{"music_id":9797,"instances":7},{"music_id":10198,"instances":7},{"music_id":1451,"instances":7},{"music_id":7634,"instances":7},{"music_id":8688,"instances":7},{"music_id":11127,"instances":7},{"music_id":7277,"instances":7},{"music_id":10708,"instances":7},{"music_id":11207,"instances":7},{"music_id":7985,"instances":7},{"music_id":10199,"instances":6},{"music_id":10642,"instances":6},{"music_id":9027,"instances":6},{"music_id":3689,"instances":6},{"music_id":7023,"instances":6},{"music_id":3692,"instances":6},{"music_id":10492,"instances":6},{"music_id":448,"instances":6},{"music_id":3686,"instances":6},{"music_id":10640,"instances":6},{"music_id":10494,"instances":6},{"music_id":5801,"instances":6},{"music_id":2138,"instances":6},{"music_id":10860,"instances":6},{"music_id":4617,"instances":6},{"music_id":792,"instances":6},{"music_id":8375,"instances":5},{"music_id":10495,"instances":5},{"music_id":447,"instances":5},{"music_id":6620,"instances":5},{"music_id":11208,"instances":5},{"music_id":5802,"instances":5},{"music_id":3688,"instances":5},{"music_id":10498,"instances":5},{"music_id":10467,"instances":5},{"music_id":870,"instances":5},{"music_id":6017,"instances":5},{"music_id":2330,"instances":5},{"music_id":1282,"instances":5},{"music_id":137,"instances":5},{"music_id":6391,"instances":5},{"music_id":10531,"instances":5},{"music_id":100,"instances":5},{"music_id":10838,"instances":5},{"music_id":1974,"instances":5},{"music_id":1740,"instances":5},{"music_id":7744,"instances":5},{"music_id":9877,"instances":4},{"music_id":10864,"instances":4},{"music_id":7279,"instances":4},{"music_id":244,"instances":4},{"music_id":7342,"instances":4},{"music_id":5056,"instances":4},{"music_id":7637,"instances":4},{"music_id":1362,"instances":4},{"music_id":10493,"instances":4},{"music_id":3687,"instances":4},{"music_id":6208,"instances":4},{"music_id":10579,"instances":4},{"music_id":9522,"instances":4},{"music_id":7636,"instances":4},{"music_id":50668,"instances":4},{"music_id":8234,"instances":4},{"music_id":5803,"instances":4},{"music_id":10393,"instances":4},{"music_id":6015,"instances":4},{"music_id":3302,"instances":4},{"music_id":27,"instances":4},{"music_id":1738,"instances":4},{"music_id":847,"instances":4},{"music_id":846,"instances":4},{"music_id":791,"instances":4},{"music_id":790,"instances":4},{"music_id":7991,"instances":4}]}