{"player_id":431,"incorrect":[{"music_id":3587,"instances":2,"total":2},{"music_id":10101,"instances":2,"total":2},{"music_id":2098,"instances":2,"total":2},{"music_id":7590,"instances":2,"total":2},{"music_id":20,"instances":2,"total":2},{"music_id":91,"instances":1,"total":1},{"music_id":1349,"instances":1,"total":1},{"music_id":37129,"instances":1,"total":1},{"music_id":1425,"instances":1,"total":1},{"music_id":1453,"instances":1,"total":1},{"music_id":9028,"instances":1,"total":1},{"music_id":14022,"instances":1,"total":1},{"music_id":24730,"instances":1,"total":1},{"music_id":12362,"instances":1,"total":1},{"music_id":1560,"instances":1,"total":1},{"music_id":4973,"instances":1,"total":1},{"music_id":22260,"instances":1,"total":1},{"music_id":17822,"instances":1,"total":1},{"music_id":13306,"instances":1,"total":1},{"music_id":2104,"instances":1,"total":1},{"music_id":14160,"instances":1,"total":1},{"music_id":11282,"instances":1,"total":1},{"music_id":1561,"instances":1,"total":1},{"music_id":13291,"instances":1,"total":1},{"music_id":37126,"instances":1,"total":1},{"music_id":12457,"instances":1,"total":1},{"music_id":12710,"instances":1,"total":1}],"never_correct":[{"music_id":3587,"instances":2,"total":2},{"music_id":10101,"instances":2,"total":2},{"music_id":2098,"instances":2,"total":2},{"music_id":7590,"instances":2,"total":2},{"music_id":20,"instances":2,"total":2},{"music_id":91,"instances":1,"total":1},{"music_id":1349,"instances":1,"total":1},{"music_id":37129,"instances":1,"total":1},{"music_id":1425,"instances":1,"total":1},{"music_id":1453,"instances":1,"total":1},{"music_id":9028,"instances":1,"total":1},{"music_id":14022,"instances":1,"total":1},{"music_id":24730,"instances":1,"total":1},{"music_id":12362,"instances":1,"total":1},{"music_id":1560,"instances":1,"total":1},{"music_id":4973,"instances":1,"total":1},{"music_id":22260,"instances":1,"total":1},{"music_id":17822,"instances":1,"total":1},{"music_id":13306,"instances":1,"total":1},{"music_id":2104,"instances":1,"total":1},{"music_id":14160,"instances":1,"total":1},{"music_id":11282,"instances":1,"total":1},{"music_id":1561,"instances":1,"total":1},{"music_id":13291,"instances":1,"total":1},{"music_id":37126,"instances":1,"total":1},{"music_id":12457,"instances":1,"total":1},{"music_id":12710,"instances":1,"total":1}]}