{"player_id":595,"incorrect":[{"music_id":28111,"instances":1,"total":1},{"music_id":13972,"instances":1,"total":1},{"music_id":13885,"instances":1,"total":1},{"music_id":3640,"instances":1,"total":1},{"music_id":27946,"instances":1,"total":1},{"music_id":30369,"instances":1,"total":1},{"music_id":13789,"instances":1,"total":1},{"music_id":35175,"instances":1,"total":1},{"music_id":17438,"instances":1,"total":1},{"music_id":15548,"instances":1,"total":1},{"music_id":5958,"instances":1,"total":1},{"music_id":10260,"instances":1,"total":1},{"music_id":9429,"instances":1,"total":1},{"music_id":20250,"instances":1,"total":1},{"music_id":6245,"instances":1,"total":1},{"music_id":11512,"instances":1,"total":1},{"music_id":99,"instances":1,"total":1},{"music_id":1408,"instances":1,"total":1},{"music_id":10494,"instances":1,"total":1},{"music_id":24928,"instances":1,"total":1},{"music_id":19441,"instances":1,"total":1},{"music_id":11148,"instances":1,"total":1},{"music_id":162,"instances":1,"total":1},{"music_id":11517,"instances":1,"total":1},{"music_id":17539,"instances":1,"total":1},{"music_id":15868,"instances":1,"total":1},{"music_id":26500,"instances":1,"total":1},{"music_id":2990,"instances":1,"total":1},{"music_id":40774,"instances":1,"total":1},{"music_id":11515,"instances":1,"total":1},{"music_id":13766,"instances":1,"total":1},{"music_id":9230,"instances":1,"total":1},{"music_id":13115,"instances":1,"total":1},{"music_id":8490,"instances":1,"total":1},{"music_id":5095,"instances":1,"total":1},{"music_id":228,"instances":1,"total":1},{"music_id":23,"instances":1,"total":1},{"music_id":6048,"instances":1,"total":1},{"music_id":29806,"instances":1,"total":1}],"never_correct":[{"music_id":28111,"instances":1,"total":1},{"music_id":13972,"instances":1,"total":1},{"music_id":13885,"instances":1,"total":1},{"music_id":3640,"instances":1,"total":1},{"music_id":27946,"instances":1,"total":1},{"music_id":30369,"instances":1,"total":1},{"music_id":13789,"instances":1,"total":1},{"music_id":35175,"instances":1,"total":1},{"music_id":17438,"instances":1,"total":1},{"music_id":15548,"instances":1,"total":1},{"music_id":5958,"instances":1,"total":1},{"music_id":10260,"instances":1,"total":1},{"music_id":9429,"instances":1,"total":1},{"music_id":20250,"instances":1,"total":1},{"music_id":6245,"instances":1,"total":1},{"music_id":11512,"instances":1,"total":1},{"music_id":99,"instances":1,"total":1},{"music_id":1408,"instances":1,"total":1},{"music_id":10494,"instances":1,"total":1},{"music_id":24928,"instances":1,"total":1},{"music_id":19441,"instances":1,"total":1},{"music_id":11148,"instances":1,"total":1},{"music_id":162,"instances":1,"total":1},{"music_id":11517,"instances":1,"total":1},{"music_id":17539,"instances":1,"total":1},{"music_id":15868,"instances":1,"total":1},{"music_id":26500,"instances":1,"total":1},{"music_id":2990,"instances":1,"total":1},{"music_id":40774,"instances":1,"total":1},{"music_id":11515,"instances":1,"total":1},{"music_id":13766,"instances":1,"total":1},{"music_id":9230,"instances":1,"total":1},{"music_id":13115,"instances":1,"total":1},{"music_id":8490,"instances":1,"total":1},{"music_id":5095,"instances":1,"total":1},{"music_id":228,"instances":1,"total":1},{"music_id":23,"instances":1,"total":1},{"music_id":6048,"instances":1,"total":1},{"music_id":29806,"instances":1,"total":1}]}