{"player_id":636,"incorrect":[{"music_id":448,"instances":8},{"music_id":77,"instances":6},{"music_id":48,"instances":6},{"music_id":10580,"instances":5},{"music_id":122,"instances":5},{"music_id":4978,"instances":5},{"music_id":2843,"instances":5},{"music_id":7932,"instances":5},{"music_id":8367,"instances":5},{"music_id":7634,"instances":5},{"music_id":244,"instances":5},{"music_id":5664,"instances":5},{"music_id":4,"instances":5},{"music_id":11225,"instances":5},{"music_id":47,"instances":5},{"music_id":8815,"instances":5},{"music_id":128,"instances":5},{"music_id":8975,"instances":4},{"music_id":145,"instances":4},{"music_id":147,"instances":4},{"music_id":153,"instances":4},{"music_id":1451,"instances":4},{"music_id":1408,"instances":4},{"music_id":2776,"instances":4},{"music_id":8816,"instances":4},{"music_id":6017,"instances":4},{"music_id":1362,"instances":4},{"music_id":5093,"instances":4},{"music_id":9382,"instances":4},{"music_id":29,"instances":4},{"music_id":227,"instances":4},{"music_id":4979,"instances":4},{"music_id":2775,"instances":4},{"music_id":58,"instances":4},{"music_id":215,"instances":4},{"music_id":5127,"instances":4},{"music_id":11838,"instances":3},{"music_id":7638,"instances":3},{"music_id":9384,"instances":3},{"music_id":2415,"instances":3},{"music_id":11632,"instances":3},{"music_id":6040,"instances":3},{"music_id":6055,"instances":3},{"music_id":2854,"instances":3},{"music_id":3686,"instances":3},{"music_id":32,"instances":3},{"music_id":150,"instances":3},{"music_id":449,"instances":3},{"music_id":6376,"instances":3},{"music_id":2987,"instances":3},{"music_id":26,"instances":3},{"music_id":7935,"instances":3},{"music_id":4713,"instances":3},{"music_id":11977,"instances":3},{"music_id":10501,"instances":3},{"music_id":243,"instances":3},{"music_id":27,"instances":3},{"music_id":5958,"instances":3},{"music_id":20,"instances":3},{"music_id":42104,"instances":3},{"music_id":46,"instances":3},{"music_id":1862,"instances":3},{"music_id":154,"instances":3},{"music_id":160,"instances":3},{"music_id":13231,"instances":3},{"music_id":146,"instances":3},{"music_id":722,"instances":3},{"music_id":2841,"instances":3},{"music_id":11517,"instances":3},{"music_id":5095,"instances":3},{"music_id":9660,"instances":3},{"music_id":164,"instances":3},{"music_id":107,"instances":3},{"music_id":33,"instances":3},{"music_id":11518,"instances":3},{"music_id":989,"instances":3},{"music_id":57,"instances":3},{"music_id":5096,"instances":3},{"music_id":24960,"instances":3},{"music_id":990,"instances":3},{"music_id":6661,"instances":2},{"music_id":218,"instances":2},{"music_id":105,"instances":2},{"music_id":11650,"instances":2},{"music_id":10445,"instances":2},{"music_id":2989,"instances":2},{"music_id":28,"instances":2},{"music_id":5276,"instances":2},{"music_id":139,"instances":2},{"music_id":7633,"instances":2},{"music_id":3961,"instances":2},{"music_id":3687,"instances":2},{"music_id":76,"instances":2},{"music_id":8814,"instances":2},{"music_id":2839,"instances":2},{"music_id":6375,"instances":2},{"music_id":12909,"instances":2},{"music_id":15361,"instances":2},{"music_id":9878,"instances":2},{"music_id":216,"instances":2}],"never_correct":[{"music_id":48,"instances":6},{"music_id":7634,"instances":5},{"music_id":4,"instances":5},{"music_id":11225,"instances":5},{"music_id":1408,"instances":4},{"music_id":5093,"instances":4},{"music_id":4979,"instances":4},{"music_id":2775,"instances":4},{"music_id":2415,"instances":3},{"music_id":6040,"instances":3},{"music_id":6055,"instances":3},{"music_id":2987,"instances":3},{"music_id":11977,"instances":3},{"music_id":42104,"instances":3},{"music_id":46,"instances":3},{"music_id":1862,"instances":3},{"music_id":13231,"instances":3},{"music_id":146,"instances":3},{"music_id":2841,"instances":3},{"music_id":33,"instances":3},{"music_id":24960,"instances":3},{"music_id":11650,"instances":2},{"music_id":2989,"instances":2},{"music_id":5276,"instances":2},{"music_id":6375,"instances":2},{"music_id":12909,"instances":2},{"music_id":15361,"instances":2},{"music_id":9878,"instances":2},{"music_id":38742,"instances":2},{"music_id":26489,"instances":2},{"music_id":5126,"instances":2},{"music_id":137,"instances":2},{"music_id":13317,"instances":2},{"music_id":42529,"instances":2},{"music_id":26505,"instances":2},{"music_id":14792,"instances":2},{"music_id":30,"instances":2},{"music_id":991,"instances":2},{"music_id":16838,"instances":2},{"music_id":222,"instances":2},{"music_id":2844,"instances":2},{"music_id":846,"instances":2},{"music_id":10261,"instances":2},{"music_id":11935,"instances":2},{"music_id":16813,"instances":2},{"music_id":228,"instances":2},{"music_id":23635,"instances":2},{"music_id":992,"instances":2},{"music_id":109,"instances":2},{"music_id":7636,"instances":2},{"music_id":805,"instances":2},{"music_id":15108,"instances":2},{"music_id":1067,"instances":2},{"music_id":10496,"instances":2},{"music_id":16807,"instances":2},{"music_id":29395,"instances":2},{"music_id":12480,"instances":2},{"music_id":20235,"instances":2},{"music_id":14096,"instances":2},{"music_id":10471,"instances":2},{"music_id":2840,"instances":2},{"music_id":17152,"instances":2},{"music_id":17692,"instances":2},{"music_id":14088,"instances":2},{"music_id":16370,"instances":2},{"music_id":12484,"instances":2},{"music_id":7635,"instances":2},{"music_id":17201,"instances":2},{"music_id":16820,"instances":2},{"music_id":17729,"instances":2},{"music_id":14835,"instances":2},{"music_id":756,"instances":1},{"music_id":42564,"instances":1},{"music_id":5908,"instances":1},{"music_id":10182,"instances":1},{"music_id":42653,"instances":1},{"music_id":33189,"instances":1},{"music_id":41150,"instances":1},{"music_id":42162,"instances":1},{"music_id":42567,"instances":1},{"music_id":24972,"instances":1},{"music_id":15543,"instances":1},{"music_id":29515,"instances":1},{"music_id":29241,"instances":1},{"music_id":8671,"instances":1},{"music_id":23077,"instances":1},{"music_id":17360,"instances":1},{"music_id":27975,"instances":1},{"music_id":7035,"instances":1},{"music_id":7856,"instances":1},{"music_id":23182,"instances":1},{"music_id":30152,"instances":1},{"music_id":30413,"instances":1},{"music_id":35261,"instances":1},{"music_id":42491,"instances":1},{"music_id":16682,"instances":1},{"music_id":879,"instances":1},{"music_id":4137,"instances":1},{"music_id":8669,"instances":1},{"music_id":10579,"instances":1}]}