{"player_id":645,"incorrect":[{"music_id":1793,"instances":1,"total":1},{"music_id":208,"instances":1,"total":1},{"music_id":24945,"instances":1,"total":1},{"music_id":13427,"instances":1,"total":1},{"music_id":23,"instances":1,"total":1},{"music_id":154,"instances":1,"total":1},{"music_id":11510,"instances":1,"total":1},{"music_id":42,"instances":1,"total":1},{"music_id":2987,"instances":1,"total":1},{"music_id":2837,"instances":1,"total":1},{"music_id":17490,"instances":1,"total":1},{"music_id":13854,"instances":1,"total":1},{"music_id":16359,"instances":1,"total":1},{"music_id":12624,"instances":1,"total":1},{"music_id":24722,"instances":1,"total":1},{"music_id":12743,"instances":1,"total":1},{"music_id":12579,"instances":1,"total":1},{"music_id":38641,"instances":1,"total":1},{"music_id":13410,"instances":1,"total":1},{"music_id":13312,"instances":1,"total":1},{"music_id":12766,"instances":1,"total":1},{"music_id":13400,"instances":1,"total":1},{"music_id":31192,"instances":1,"total":1},{"music_id":28169,"instances":1,"total":1},{"music_id":28216,"instances":1,"total":1},{"music_id":12393,"instances":1,"total":1}],"never_correct":[{"music_id":1793,"instances":1,"total":1},{"music_id":208,"instances":1,"total":1},{"music_id":24945,"instances":1,"total":1},{"music_id":13427,"instances":1,"total":1},{"music_id":23,"instances":1,"total":1},{"music_id":154,"instances":1,"total":1},{"music_id":11510,"instances":1,"total":1},{"music_id":42,"instances":1,"total":1},{"music_id":2987,"instances":1,"total":1},{"music_id":2837,"instances":1,"total":1},{"music_id":17490,"instances":1,"total":1},{"music_id":13854,"instances":1,"total":1},{"music_id":16359,"instances":1,"total":1},{"music_id":12624,"instances":1,"total":1},{"music_id":24722,"instances":1,"total":1},{"music_id":12743,"instances":1,"total":1},{"music_id":12579,"instances":1,"total":1},{"music_id":38641,"instances":1,"total":1},{"music_id":13410,"instances":1,"total":1},{"music_id":13312,"instances":1,"total":1},{"music_id":12766,"instances":1,"total":1},{"music_id":13400,"instances":1,"total":1},{"music_id":31192,"instances":1,"total":1},{"music_id":28169,"instances":1,"total":1},{"music_id":28216,"instances":1,"total":1},{"music_id":12393,"instances":1,"total":1}]}