{"player_id":974,"incorrect":[{"music_id":11368,"instances":1,"total":1},{"music_id":3301,"instances":1,"total":1},{"music_id":5094,"instances":1,"total":1},{"music_id":12020,"instances":1,"total":1},{"music_id":28584,"instances":1,"total":1},{"music_id":20467,"instances":1,"total":1},{"music_id":35939,"instances":1,"total":1},{"music_id":2137,"instances":1,"total":1},{"music_id":42196,"instances":1,"total":1},{"music_id":1020,"instances":1,"total":1},{"music_id":6246,"instances":1,"total":1},{"music_id":9380,"instances":1,"total":1},{"music_id":18327,"instances":1,"total":1},{"music_id":10446,"instances":1,"total":1}],"never_correct":[{"music_id":11368,"instances":1,"total":1},{"music_id":3301,"instances":1,"total":1},{"music_id":5094,"instances":1,"total":1},{"music_id":12020,"instances":1,"total":1},{"music_id":28584,"instances":1,"total":1},{"music_id":20467,"instances":1,"total":1},{"music_id":35939,"instances":1,"total":1},{"music_id":2137,"instances":1,"total":1},{"music_id":42196,"instances":1,"total":1},{"music_id":1020,"instances":1,"total":1},{"music_id":6246,"instances":1,"total":1},{"music_id":9380,"instances":1,"total":1},{"music_id":18327,"instances":1,"total":1},{"music_id":10446,"instances":1,"total":1}]}